complete_confusion/__init__.py
complete_confusion/confusion_matrix.html
complete_confusion/evaluate.py
complete_confusion/template.html
complete_confusion-0.1.0.dist-info/LICENSE
complete_confusion-0.1.0.dist-info/METADATA
complete_confusion-0.1.0.dist-info/WHEEL
complete_confusion-0.1.0.dist-info/RECORD
